{"moduleName":null,"summaries":[{"symbol":{"__symbol":0,"members":[]},"metadata":{"__symbolic":"interface"}},{"symbol":{"__symbol":1,"members":[]},"metadata":{"__symbolic":"interface"}},{"symbol":{"__symbol":2,"members":[]},"metadata":{"__symbolic":"interface"}},{"symbol":{"__symbol":3,"members":[]},"metadata":{"__symbolic":"interface"}},{"symbol":{"__symbol":4,"members":[]},"metadata":{"__symbolic":"interface"}},{"symbol":{"__symbol":5,"members":[]},"metadata":{"__symbolic":"interface"}},{"symbol":{"__symbol":6,"members":[]},"metadata":{"__symbolic":"interface"}},{"symbol":{"__symbol":7,"members":[]},"metadata":{"__symbolic":"interface"}},{"symbol":{"__symbol":8,"members":[]},"metadata":{"__symbolic":"interface"}},{"symbol":{"__symbol":9,"members":[]},"metadata":{"__symbolic":"interface"}},{"symbol":{"__symbol":10,"members":[]},"metadata":{"__symbolic":"interface"}},{"symbol":{"__symbol":11,"members":[]},"metadata":{"__symbolic":"interface"}},{"symbol":{"__symbol":12,"members":[]},"metadata":{"__symbolic":"interface"}},{"symbol":{"__symbol":13,"members":[]},"metadata":{"__symbolic":"interface"}},{"symbol":{"__symbol":14,"members":[]},"metadata":{"__symbolic":"interface"}}],"symbols":[{"__symbol":0,"name":"ValueSansProvider","filePath":"./provider"},{"__symbol":1,"name":"ValueProvider","filePath":"./provider"},{"__symbol":2,"name":"StaticClassSansProvider","filePath":"./provider"},{"__symbol":3,"name":"StaticClassProvider","filePath":"./provider"},{"__symbol":4,"name":"ConstructorSansProvider","filePath":"./provider"},{"__symbol":5,"name":"ConstructorProvider","filePath":"./provider"},{"__symbol":6,"name":"ExistingSansProvider","filePath":"./provider"},{"__symbol":7,"name":"ExistingProvider","filePath":"./provider"},{"__symbol":8,"name":"FactorySansProvider","filePath":"./provider"},{"__symbol":9,"name":"FactoryProvider","filePath":"./provider"},{"__symbol":10,"name":"StaticProvider","filePath":"./provider"},{"__symbol":11,"name":"TypeProvider","filePath":"./provider"},{"__symbol":12,"name":"ClassSansProvider","filePath":"./provider"},{"__symbol":13,"name":"ClassProvider","filePath":"./provider"},{"__symbol":14,"name":"Provider","filePath":"./provider"}]}